{
  "main": {
    "id": "151c5920ed201045",
    "type": "split",
    "children": [
      {
        "id": "b715c43fedc72926",
        "type": "tabs",
        "children": [
          {
            "id": "87c3c5f9f85fe5cd",
            "type": "leaf",
            "state": {
              "type": "markdown",
              "state": {
                "file": "Babysuid 50.md",
                "mode": "source",
                "source": false
              }
            }
          },
          {
            "id": "e8fa49daf10ff471",
            "type": "leaf",
            "state": {
              "type": "markdown",
              "state": {
                "file": "Babysuid 51.md",
                "mode": "source",
                "source": false
              }
            }
          }
        ],
        "currentTab": 1
      }
    ],
    "direction": "vertical"
  },
  "left": {
    "id": "aa9a9ad49ec5603e",
    "type": "split",
    "children": [
      {
        "id": "d3c24daa39868400",
        "type": "tabs",
        "children": [
          {
            "id": "5b6c677db574a809",
            "type": "leaf",
            "state": {
              "type": "file-explorer",
              "state": {
                "sortOrder": "alphabetical"
              }
            }
          },
          {
            "id": "4306e4b1fa03b4c4",
            "type": "leaf",
            "state": {
              "type": "search",
              "state": {
                "query": "",
                "matchingCase": false,
                "explainSearch": false,
                "collapseAll": false,
                "extraContext": false,
                "sortOrder": "alphabetical"
              }
            }
          },
          {
            "id": "4f84d91be7fe5bdc",
            "type": "leaf",
            "state": {
              "type": "bookmarks",
              "state": {}
            }
          }
        ]
      }
    ],
    "direction": "horizontal",
    "width": 300
  },
  "right": {
    "id": "2fdc2ef2b0d6e440",
    "type": "split",
    "children": [
      {
        "id": "724d4b42dc306253",
        "type": "tabs",
        "children": [
          {
            "id": "0e474ec004c59d07",
            "type": "leaf",
            "state": {
              "type": "backlink",
              "state": {
                "file": "Babysuid 51.md",
                "collapseAll": false,
                "extraContext": false,
                "sortOrder": "alphabetical",
                "showSearch": false,
                "searchQuery": "",
                "backlinkCollapsed": false,
                "unlinkedCollapsed": true
              }
            }
          },
          {
            "id": "46589ac111902b73",
            "type": "leaf",
            "state": {
              "type": "outgoing-link",
              "state": {
                "file": "Babysuid 51.md",
                "linksCollapsed": false,
                "unlinkedCollapsed": true
              }
            }
          },
          {
            "id": "96e05996cc8747b0",
            "type": "leaf",
            "state": {
              "type": "tag",
              "state": {
                "sortOrder": "frequency",
                "useHierarchy": true
              }
            }
          },
          {
            "id": "293b40366d194ee5",
            "type": "leaf",
            "state": {
              "type": "outline",
              "state": {
                "file": "Babysuid 51.md"
              }
            }
          }
        ]
      }
    ],
    "direction": "horizontal",
    "width": 300,
    "collapsed": true
  },
  "left-ribbon": {
    "hiddenItems": {
      "switcher:Open quick switcher": false,
      "graph:Open graph view": false,
      "canvas:Create new canvas": false,
      "daily-notes:Open today's daily note": false,
      "templates:Insert template": false,
      "command-palette:Open command palette": false
    }
  },
  "active": "e8fa49daf10ff471",
  "lastOpenFiles": [
    "Babysuid 50.md",
    "Babysuid 51.md",
    "README.md"
  ]
}